{
  "posts": [
    {
      "id": "1",
      "title": "json-server",
      "userId": "1"
    },
    {
      "id": "2",
      "title": "json-server",
      "userId": "2"
    }
  ],
  "comments": [
    {
      "id": "1",
      "body": "some comment",
      "postId": "1"
    }
  ],
  "users": [
    {
      "id": "1",
      "username": "admin",
      "password": "123"
    },
    {
      "id": "2",
      "username": "user",
      "password": "123"
    }
  ],
  "profiles": [{
    "first_name": "Viktory",
    "last_name": "B.",
    "age": 22,
    "currency": "EUR",
    "country": "Portugal",
    "city": "Porto",
    "username": "admin",
    "id": "1",
    "avatar": "https://i.imgur.com/g6AWyos.jpg"
  },
  {
    "first_name": "Veles",
    "last_name": "Pan",
    "age": 999,
    "currency": "EUR",
    "country": "Portugal",
    "city": "Porto",
    "username": "user",
    "id": "2",
    "avatar": "https://i.imgur.com/UvBboIO.jpg"
  }]
}
